{"rules":{},"filters":{"FileCreate_Windows":{"rules":[],"parameters":[]},"IsNormalizedEvent":{"rules":[],"parameters":[]},"IsProcessStartEvent":{"rules":[],"parameters":[{"string":"name"}]},"LoginAttempt_Windows_Endpoint":{"rules":[],"parameters":[]},"NotFromCorrelator":{"rules":[],"parameters":[]},"OperatingSystem_UNIXLike":{"rules":[],"parameters":[]},"ProcessStart_Windows_any":{"rules":[],"parameters":[]},"ProcessStart_Windows_cmd_meta":{"rules":[],"parameters":[{"string":"name"},{"string":"commandline_regex"},{"string":"object_meta"}]},"ProcessStart_Windows_commandline":{"rules":[],"parameters":[{"string":"name"},{"string":"commandline_regex"}]},"UserAccount_Windows":{"rules":[],"parameters":[{"string":"name"},{"string":"id"}]}},"table_bindings":{}}